{"slug":"discovery","last_updated":"2026-03-14T18:41:09Z","snotel_stations":[{"name":"Barker Lakes","triplet":"313:MT:SNTL","elevation_ft":8250,"distance_mi":0,"latest":{"date":"2026-03-13","snow_depth_in":40.0,"swe_in":9.8,"temp_f":30.0,"precip_accum_in":15.6},"history_7d":[{"date":"2026-03-07","snow_depth_in":37.0,"swe_in":8.8},{"date":"2026-03-08","snow_depth_in":35.0,"swe_in":8.8},{"date":"2026-03-09","snow_depth_in":37.0,"swe_in":8.8},{"date":"2026-03-10","snow_depth_in":37.0,"swe_in":8.8},{"date":"2026-03-11","snow_depth_in":36.0,"swe_in":9.0},{"date":"2026-03-12","snow_depth_in":38.0,"swe_in":9.4},{"date":"2026-03-13","snow_depth_in":40.0,"swe_in":9.8}]},{"name":"Warm Springs","triplet":"850:MT:SNTL","elevation_ft":7840,"distance_mi":0,"latest":{"date":"2026-03-13","snow_depth_in":84.0,"swe_in":24.4,"temp_f":30.9,"precip_accum_in":26.3},"history_7d":[{"date":"2026-03-07","snow_depth_in":71.0,"swe_in":21.4},{"date":"2026-03-08","snow_depth_in":69.0,"swe_in":21.4},{"date":"2026-03-09","snow_depth_in":69.0,"swe_in":21.4},{"date":"2026-03-10","snow_depth_in":68.0,"swe_in":21.4},{"date":"2026-03-11","snow_depth_in":68.0,"swe_in":21.4},{"date":"2026-03-12","snow_depth_in":74.0,"swe_in":22.5},{"date":"2026-03-13","snow_depth_in":84.0,"swe_in":24.4}]},{"name":"Peterson Meadows","triplet":"930:MT:SNTL","elevation_ft":7190,"distance_mi":0,"latest":{"date":"2026-03-13","snow_depth_in":38.0,"swe_in":9.2,"temp_f":32.0,"precip_accum_in":13.3},"history_7d":[{"date":"2026-03-07","snow_depth_in":34.0,"swe_in":8.2},{"date":"2026-03-08","snow_depth_in":33.0,"swe_in":8.2},{"date":"2026-03-09","snow_depth_in":33.0,"swe_in":8.2},{"date":"2026-03-10","snow_depth_in":33.0,"swe_in":8.3},{"date":"2026-03-11","snow_depth_in":33.0,"swe_in":8.4},{"date":"2026-03-12","snow_depth_in":37.0,"swe_in":9.0},{"date":"2026-03-13","snow_depth_in":38.0,"swe_in":9.2}]}]}