{"slug":"purgatory","last_updated":"2026-03-07T06:43:25Z","snotel_stations":[{"name":"Cascade #2","triplet":"387:CO:SNTL","elevation_ft":8990,"distance_mi":0,"latest":{"date":"2026-03-05","snow_depth_in":0.0,"swe_in":0.8,"temp_f":30.4,"precip_accum_in":15.6},"history_7d":[{"date":"2026-02-28","snow_depth_in":4.0,"swe_in":2.7},{"date":"2026-03-01","snow_depth_in":3.0,"swe_in":2.3},{"date":"2026-03-02","snow_depth_in":2.0,"swe_in":2.2},{"date":"2026-03-03","snow_depth_in":2.0,"swe_in":1.7},{"date":"2026-03-04","snow_depth_in":1.0,"swe_in":1.2},{"date":"2026-03-05","snow_depth_in":0.0,"swe_in":0.8}]},{"name":"Molas Lake","triplet":"632:CO:SNTL","elevation_ft":10610,"distance_mi":0,"latest":{"date":"2026-03-05","snow_depth_in":27.0,"swe_in":7.5,"temp_f":24.6,"precip_accum_in":15.3},"history_7d":[{"date":"2026-02-28","snow_depth_in":29.0,"swe_in":7.6},{"date":"2026-03-01","snow_depth_in":28.0,"swe_in":7.6},{"date":"2026-03-02","snow_depth_in":28.0,"swe_in":7.6},{"date":"2026-03-03","snow_depth_in":28.0,"swe_in":7.5},{"date":"2026-03-04","snow_depth_in":27.0,"swe_in":7.6},{"date":"2026-03-05","snow_depth_in":27.0,"swe_in":7.5}]},{"name":"Spud Mountain","triplet":"780:CO:SNTL","elevation_ft":10660,"distance_mi":0,"latest":{"date":"2026-03-05","snow_depth_in":35.0,"swe_in":11.0,"temp_f":23.5,"precip_accum_in":22.0},"history_7d":[{"date":"2026-02-28","snow_depth_in":40.0,"swe_in":11.2},{"date":"2026-03-01","snow_depth_in":38.0,"swe_in":11.1},{"date":"2026-03-02","snow_depth_in":37.0,"swe_in":11.1},{"date":"2026-03-03","snow_depth_in":37.0,"swe_in":11.1},{"date":"2026-03-04","snow_depth_in":36.0,"swe_in":11.0},{"date":"2026-03-05","snow_depth_in":35.0,"swe_in":11.0}]}]}