{"slug":"ski-apache","last_updated":"2026-03-07T12:43:31Z","snotel_stations":[{"name":"Sierra Blanca","triplet":"1034:NM:SNTL","elevation_ft":10250,"distance_mi":0,"latest":{"date":"2026-03-06","snow_depth_in":0.0,"swe_in":0.0,"temp_f":29.3,"precip_accum_in":11.0},"history_7d":[{"date":"2026-02-28","snow_depth_in":0.0,"swe_in":0.0},{"date":"2026-03-01","snow_depth_in":0.0,"swe_in":0.0},{"date":"2026-03-02","snow_depth_in":0.0,"swe_in":0.0},{"date":"2026-03-03","snow_depth_in":0.0,"swe_in":0.0},{"date":"2026-03-04","snow_depth_in":0.0,"swe_in":0.0},{"date":"2026-03-05","snow_depth_in":0.0,"swe_in":0.0},{"date":"2026-03-06","snow_depth_in":0.0,"swe_in":0.0}]}]}